{
  "trigger": true,
  "modules": [
    "add-to-group"
  ],
  "parentResource": "scrapingf3c6ba39",
  "functionName": "scrapingf3c6ba39PostConfirmation",
  "resourceName": "scrapingf3c6ba39PostConfirmation",
  "parentStack": "auth",
  "triggerEnvs": "[]",
  "triggerDir": "C:\\snapshot\\repo\\build\\node_modules\\@aws-amplify\\amplify-category-auth\\provider-utils\\awscloudformation\\triggers\\PostConfirmation",
  "triggerTemplate": "PostConfirmation.json.ejs",
  "triggerEventPath": "PostConfirmation.event.json",
  "roleName": "scrapingf3c6ba39PostConfirmation",
  "skipEdit": true
}